{
  "ourServices": [
    {
      "TabName": "Engineering Services",
      "title": "Engineering Services",
      "description": "Solutions that are engineered to perfection, specifically for the engineering sector.",
      "serviceBlocks": [
        {
          "title": "Quality Control",
          "description": "With the help of experienced developers and designers, we make apps that are highly usable.",
          "actionButton": "Read more",
          "blockSize": "medium"
        },
        {
          "title": "Application Development",
          "description": "With the help of experienced developers and designers, we make apps that are highly usable",
          "actionButton": "Read more",
          "blockSize": "medium"
        }
      ]
    }
  ]
}